django_wamp_client-0.0.3.dist-info/DESCRIPTION.rst
django_wamp_client-0.0.3.dist-info/METADATA
django_wamp_client-0.0.3.dist-info/RECORD
django_wamp_client-0.0.3.dist-info/WHEEL
django_wamp_client-0.0.3.dist-info/metadata.json
django_wamp_client-0.0.3.dist-info/top_level.txt
wampclient/__init__.py
wampclient/conf.py
wampclient/management/__init__.py
wampclient/management/commands/__init__.py
wampclient/management/commands/wamp_client.py
